README.md
setup.py
DeepVision_Toolkit.egg-info/PKG-INFO
DeepVision_Toolkit.egg-info/SOURCES.txt
DeepVision_Toolkit.egg-info/dependency_links.txt
DeepVision_Toolkit.egg-info/requires.txt
DeepVision_Toolkit.egg-info/top_level.txt
deepvision/__init__.py
deepvision/datasets/__init__.py
deepvision/datasets/tiny_nerf/__init__.py
deepvision/datasets/tiny_nerf/tiny_nerf.py
deepvision/datasets/tiny_nerf/tiny_nerf_pt.py
deepvision/datasets/tiny_nerf/tiny_nerf_tf.py
deepvision/evaluation/__init__.py
deepvision/evaluation/feature_analysis.py
deepvision/layers/__init__.py
deepvision/layers/efficient_attention.py
deepvision/layers/fused_mbconv.py
deepvision/layers/hierarchical_transformer_encoder.py
deepvision/layers/identity.py
deepvision/layers/mbconv.py
deepvision/layers/mix_ffn.py
deepvision/layers/overlapping_patching_and_embedding.py
deepvision/layers/patching_and_embedding.py
deepvision/layers/segformer_segmentation_head.py
deepvision/layers/stochasticdepth.py
deepvision/layers/transformer_encoder.py
deepvision/losses/__init__.py
deepvision/models/__init__.py
deepvision/models/load_weights.py
deepvision/models/classification/__init__.py
deepvision/models/classification/efficientnet/__init__.py
deepvision/models/classification/efficientnet/efficientnet_weight_mapper.py
deepvision/models/classification/efficientnet/efficientnetv2.py
deepvision/models/classification/efficientnet/efficientnetv2_pt.py
deepvision/models/classification/efficientnet/efficientnetv2_tf.py
deepvision/models/classification/mix_transformer/__init__.py
deepvision/models/classification/mix_transformer/mit.py
deepvision/models/classification/mix_transformer/mit_pt.py
deepvision/models/classification/mix_transformer/mit_tf.py
deepvision/models/classification/resnet/__init__.py
deepvision/models/classification/resnet/resnetv2.py
deepvision/models/classification/resnet/resnetv2_pt.py
deepvision/models/classification/resnet/resnetv2_tf.py
deepvision/models/classification/vision_transformer/__init__.py
deepvision/models/classification/vision_transformer/vit.py
deepvision/models/classification/vision_transformer/vit_pt.py
deepvision/models/classification/vision_transformer/vit_tf.py
deepvision_toolkit.egg-info/PKG-INFO
deepvision_toolkit.egg-info/SOURCES.txt
deepvision_toolkit.egg-info/dependency_links.txt
deepvision_toolkit.egg-info/requires.txt
deepvision_toolkit.egg-info/top_level.txt
