Metadata-Version: 1.1
Name: deepvision-toolkit
Version: 0.1.6
Summary: PyTorch and TensorFlow/Keras image models with automatic weight conversions and equal API/implementations - Vision Transformer (ViT), ResNetV2, EfficientNetV2, NeRFs, MixTransformers, SegFormer, (planned DeepLabV3+, ConvNeXtV2, YOLO, etc.)
Home-page: https://github.com/DavidLandup0/deepvision
Author: David Landup
Author-email: david.landup.0@gmail.com
License: Apache License 2.0
Platform: UNKNOWN
Classifier: Development Status :: 1 - Planning
Classifier: Intended Audience :: Science/Research
Classifier: License :: OSI Approved :: Apache Software License
Classifier: Programming Language :: Python :: 3.9
Classifier: Topic :: Scientific/Engineering
Classifier: Topic :: Software Development
